{
    "num": 2,
    "name": "運命の5分間",
    "description": "索敵機が敵空母艦隊を発見！第二次攻撃命令で混乱した敵に急降下爆撃を決行せよ！",
    "box": [
        "1",
        "2"
    ],
    "blueprint": {
        "purple": [
            "127mm単装砲T3A",
            "油圧カタパルトT2",
            "SB2CヘルダイバーT3"
        ],
        "blue": [
            "102mm単装砲(副砲)T3",
            "152mm単装砲T3B"
        ]
    },
    "character": {
        "sr": [
            "チャールズ・オースバーン",
            "ラフィー",
            "ジャベリン",
            "綾波",
            "蒼龍",
            "飛龍"
        ],
        "r": [
            "シムス",
            "ハムマン",
            "フォーチュン",
            "アリシューザ",
            "ガラティア"
        ],
        "n": [
            "カッシン",
            "ダウンズ",
            "クレイヴン",
            "マッコール",
            "オマハ",
            "ローリー",
            "ネバダ",
            "オクラホマ",
            "ラングレー",
            "レンジャー",
            "フォックスハウンド",
            "カールスルーエ",
            "ケルン",
            "ケーニヒスベルク"
        ]
    }
}